{
  "book": {
    "abbrev": { "pt": "sl", "en": "ps" },
    "name": "Salmos",
    "author": "David, Moisés, Salomão",
    "group": "Poéticos",
    "version": "acf"
  },
  "chapter": { "number": 119, "verses": 176 },
  "verses": [
    {
      "number": 1,
      "text": "Bem-aventurados os retos em seus caminhos, que andam na lei do Senhor."
    },
    {
      "number": 2,
      "text": "Bem-aventurados os que guardam os seus testemunhos, e que o buscam com todo o coração."
    },
    {
      "number": 3,
      "text": "E não praticam iniqüidade, mas andam nos seus caminhos."
    },
    {
      "number": 4,
      "text": "Tu ordenaste os teus mandamentos, para que diligentemente os observássemos."
    },
    {
      "number": 5,
      "text": "Quem dera que os meus caminhos fossem dirigidos a observar os teus mandamentos."
    },
    {
      "number": 6,
      "text": "Então não ficaria confundido, atentando eu para todos os teus mandamentos."
    },
    {
      "number": 7,
      "text": "Louvar-te-ei com retidão de coração quando tiver aprendido os teus justos juízos."
    },
    {
      "number": 8,
      "text": "Observarei os teus estatutos; não me desampares totalmente."
    },
    {
      "number": 9,
      "text": "Com que purificará o jovem o seu caminho? Observando-o conforme a tua palavra."
    },
    {
      "number": 10,
      "text": "Com todo o meu coração te busquei; não me deixes desviar dos teus mandamentos."
    },
    {
      "number": 11,
      "text": "Escondi a tua palavra no meu coração, para eu não pecar contra ti."
    },
    {
      "number": 12,
      "text": "Bendito és tu, ó Senhor; ensina-me os teus estatutos."
    },
    {
      "number": 13,
      "text": "Com os meus lábios declarei todos os juízos da tua boca."
    },
    {
      "number": 14,
      "text": "Folguei tanto no caminho dos teus testemunhos, como em todas as riquezas."
    },
    {
      "number": 15,
      "text": "Meditarei nos teus preceitos, e terei respeito aos teus caminhos."
    },
    {
      "number": 16,
      "text": "Recrear-me-ei nos teus estatutos; não me esquecerei da tua palavra."
    },
    {
      "number": 17,
      "text": "Faze bem ao teu servo, para que viva e observe a tua palavra."
    },
    {
      "number": 18,
      "text": "Abre tu os meus olhos, para que veja as maravilhas da tua lei."
    },
    {
      "number": 19,
      "text": "Sou peregrino na terra; não escondas de mim os teus mandamentos."
    },
    {
      "number": 20,
      "text": "A minha alma está quebrantada de desejar os teus juízos em todo o tempo."
    },
    {
      "number": 21,
      "text": "Tu repreendeste asperamente os soberbos que são amaldiçoa-dos, que se desviam dos teus mandamentos."
    },
    {
      "number": 22,
      "text": "Tira de sobre mim o opróbrio e o desprezo, pois guardei os teus testemunhos."
    },
    {
      "number": 23,
      "text": "Príncipes também se assentaram, e falaram contra mim, mas o teu servo meditou nos teus estatutos."
    },
    {
      "number": 24,
      "text": "Também os teus testemunhos são o meu prazer e os meus conselheiros."
    },
    {
      "number": 25,
      "text": "A minha alma está pegada ao pó; vivifica-me segundo a tua palavra."
    },
    {
      "number": 26,
      "text": "Eu te contei os meus caminhos, e tu me ouviste; ensina-me os teus estatutos."
    },
    {
      "number": 27,
      "text": "Faze-me entender o caminho dos teus preceitos; assim falarei das tuas maravilhas."
    },
    {
      "number": 28,
      "text": "A minha alma consome-se de tristeza; fortalece-me segundo a tua palavra."
    },
    {
      "number": 29,
      "text": "Desvia de mim o caminho da falsidade, e concede-me piedosamente a tua lei."
    },
    {
      "number": 30,
      "text": "Escolhi o caminho da verdade; propus-me seguir os teus juízos."
    },
    {
      "number": 31,
      "text": "Apego-me aos teus testemunhos; ó Senhor, não me confundas."
    },
    {
      "number": 32,
      "text": "Correrei pelo caminho dos teus mandamentos, quando dilatares o meu coração."
    },
    {
      "number": 33,
      "text": "Ensina-me, ó Senhor, o caminho dos teus estatutos, e guardá-lo-ei até o fim."
    },
    {
      "number": 34,
      "text": "Dá-me entendimento, e guardarei a tua lei, e observá-la-ei de todo o meu coração."
    },
    {
      "number": 35,
      "text": "Faze-me andar na vereda dos teus mandamentos, porque nela tenho prazer."
    },
    {
      "number": 36,
      "text": "Inclina o meu coração aos teus testemunhos, e não à cobiça."
    },
    {
      "number": 37,
      "text": "Desvia os meus olhos de contemplarem a vaidade, e vivifica-me no teu caminho."
    },
    {
      "number": 38,
      "text": "Confirma a tua palavra ao teu servo, que é dedicado ao teu temor."
    },
    {
      "number": 39,
      "text": "Desvia de mim o opróbrio que temo, pois os teus juízos são bons."
    },
    {
      "number": 40,
      "text": "Eis que tenho desejado os teus preceitos; vivifica-me na tua justiça."
    },
    {
      "number": 41,
      "text": "Venham sobre mim também as tuas misericórdias, ó Senhor, e a tua salvação segundo a tua palavra."
    },
    {
      "number": 42,
      "text": "Assim terei que responder ao que me afronta, pois confio na tua palavra."
    },
    {
      "number": 43,
      "text": "E não tires totalmente a palavra de verdade da minha boca, pois tenho esperado nos teus juízos."
    },
    {
      "number": 44,
      "text": "Assim observarei de contínuo a tua lei para sempre e eternamente."
    },
    {
      "number": 45,
      "text": "E andarei em liberdade; pois busco os teus preceitos."
    },
    {
      "number": 46,
      "text": "Também falarei dos teus testemunhos perante os reis, e não me envergonharei."
    },
    {
      "number": 47,
      "text": "E recrear-me-ei em teus mandamentos, que tenho amado."
    },
    {
      "number": 48,
      "text": "Também levantarei as minhas mãos para os teus mandamentos, que amei, e meditarei nos teus estatutos."
    },
    {
      "number": 49,
      "text": "Lembra-te da palavra dada ao teu servo, na qual me fizeste esperar."
    },
    {
      "number": 50,
      "text": "Isto é a minha consolação na minha aflição, porque a tua palavra me vivificou."
    },
    {
      "number": 51,
      "text": "Os soberbos zombaram grandemente de mim; contudo não me desviei da tua lei."
    },
    {
      "number": 52,
      "text": "Lembrei-me dos teus juízos antiqüíssimos, ó Senhor, e assim me consolei."
    },
    {
      "number": 53,
      "text": "Grande indignação se apoderou de mim por causa dos ímpios que abandonam a tua lei."
    },
    {
      "number": 54,
      "text": "Os teus estatutos têm sido os meus cânticos na casa da minha peregrinação."
    },
    {
      "number": 55,
      "text": "Lembrei-me do teu nome, ó Senhor, de noite, e observei a tua lei."
    },
    {
      "number": 56,
      "text": "Isto fiz eu, porque guardei os teus mandamentos."
    },
    {
      "number": 57,
      "text": "O Senhor é a minha porção; eu disse que observaria as tuas palavras."
    },
    {
      "number": 58,
      "text": "Roguei deveras o teu favor com todo o meu coração; tem piedade de mim, segundo a tua palavra."
    },
    {
      "number": 59,
      "text": "Considerei os meus caminhos, e voltei os meus pés para os teus testemunhos."
    },
    {
      "number": 60,
      "text": "Apressei-me, e não me detive, a observar os teus mandamentos."
    },
    {
      "number": 61,
      "text": "Bandos de ímpios me despojaram, mas eu não me esqueci da tua lei."
    },
    {
      "number": 62,
      "text": "À meia-noite me levantarei para te louvar, pelos teus justos juízos."
    },
    {
      "number": 63,
      "text": "Companheiro sou de todos os que te temem e dos que guardam os teus preceitos."
    },
    {
      "number": 64,
      "text": "A terra, ó Senhor, está cheia da tua benignidade; ensina-me os teus estatutos."
    },
    {
      "number": 65,
      "text": "Fizeste bem ao teu servo, Senhor, segundo a tua palavra."
    },
    {
      "number": 66,
      "text": "Ensina-me bom juízo e ciência, pois cri nos teus mandamentos."
    },
    {
      "number": 67,
      "text": "Antes de ser afligido andava errado; mas agora tenho guardado a tua palavra."
    },
    {
      "number": 68,
      "text": "Tu és bom e fazes bem; ensina-me os teus estatutos."
    },
    {
      "number": 69,
      "text": "Os soberbos forjaram mentiras contra mim; mas eu com todo o meu coração guardarei os teus preceitos."
    },
    {
      "number": 70,
      "text": "Engrossa-se-lhes o coração como gordura, mas eu me recreio na tua lei."
    },
    {
      "number": 71,
      "text": "Foi-me bom ter sido afligido, para que aprendesse os teus estatutos."
    },
    {
      "number": 72,
      "text": "Melhor é para mim a lei da tua boca do que milhares de ouro ou prata."
    },
    {
      "number": 73,
      "text": "As tuas mãos me fizeram e me formaram; dá-me inteligência para entender os teus mandamentos."
    },
    {
      "number": 74,
      "text": "Os que te temem alegraram-se quando me viram, porque tenho esperado na tua palavra."
    },
    {
      "number": 75,
      "text": "Bem sei eu, ó Senhor, que os teus juízos são justos, e que segundo a tua fidelidade me afligiste."
    },
    {
      "number": 76,
      "text": "Sirva pois a tua benignidade para me consolar, segundo a palavra que deste ao teu servo."
    },
    {
      "number": 77,
      "text": "Venham sobre mim as tuas misericórdias, para que viva, pois a tua lei é a minha delícia."
    },
    {
      "number": 78,
      "text": "Confundam-se os soberbos, pois me trataram duma maneira perversa, sem causa; mas eu meditarei nos teus preceitos."
    },
    {
      "number": 79,
      "text": "Voltem-se para mim os que te temem, e aqueles que têm conhecido os teus testemunhos."
    },
    {
      "number": 80,
      "text": "Seja reto o meu coração nos teus estatutos, para que não seja confundido."
    },
    {
      "number": 81,
      "text": "Desfalece a minha alma pela tua salvação, mas espero na tua palavra."
    },
    {
      "number": 82,
      "text": "Os meus olhos desfalecem pela tua palavra; entrementes dizia: Quando me consolarás tu?"
    },
    {
      "number": 83,
      "text": "Pois estou como odre na fumaça; contudo não me esqueço dos teus estatutos."
    },
    {
      "number": 84,
      "text": "Quantos serão os dias do teu servo? Quando me farás justiça contra os que me perseguem?"
    },
    {
      "number": 85,
      "text": "Os soberbos me cavaram covas, o que não é conforme a tua lei."
    },
    {
      "number": 86,
      "text": "Todos os teus mandamentos são verdade. Com mentiras me perseguem; ajuda-me."
    },
    {
      "number": 87,
      "text": "Quase que me têm consumido sobre a terra, mas eu não deixei os teus preceitos."
    },
    {
      "number": 88,
      "text": "Vivifica-me segundo a tua benignidade; assim guardarei o testemunho da tua boca."
    },
    {
      "number": 89,
      "text": "Para sempre, ó Senhor, a tua palavra permanece no céu."
    },
    {
      "number": 90,
      "text": "A tua fidelidade dura de geração em geração; tu firmaste a terra, e ela permanece firme."
    },
    {
      "number": 91,
      "text": "Eles continuam até ao dia de hoje, segundo as tuas ordenações; porque todos são teus servos."
    },
    {
      "number": 92,
      "text": "Se a tua lei não fora toda a minha recreação, há muito que pereceria na minha aflição."
    },
    {
      "number": 93,
      "text": "Nunca me esquecerei dos teus preceitos; pois por eles me tens vivificado."
    },
    {
      "number": 94,
      "text": "Sou teu, salva-me; pois tenho buscado os teus preceitos."
    },
    {
      "number": 95,
      "text": "Os ímpios me esperam para me destruírem, mas eu considerarei os teus testemunhos."
    },
    {
      "number": 96,
      "text": "Tenho visto fim a toda a perfeição, mas o teu mandamento é amplíssimo."
    },
    {
      "number": 97,
      "text": "Oh! quanto amo a tua lei! É a minha meditação em todo o dia."
    },
    {
      "number": 98,
      "text": "Tu, pelos teus mandamentos, me fazes mais sábio do que os meus inimigos; pois estão sempre comigo."
    },
    {
      "number": 99,
      "text": "Tenho mais entendimento do que todos os meus mestres, porque os teus testemunhos são a minha meditação."
    },
    {
      "number": 100,
      "text": "Entendo mais do que os antigos; porque guardo os teus preceitos."
    },
    {
      "number": 101,
      "text": "Desviei os meus pés de todo caminho mau, para guardar a tua palavra."
    },
    {
      "number": 102,
      "text": "Não me apartei dos teus juízos, pois tu me ensinaste."
    },
    {
      "number": 103,
      "text": "Oh! quão doces são as tuas palavras ao meu paladar, mais doces do que o mel à minha boca."
    },
    {
      "number": 104,
      "text": "Pelos teus mandamentos alcancei entendimento; por isso odeio todo falso caminho."
    },
    {
      "number": 105,
      "text": "Lâmpada para os meus pés é tua palavra, e luz para o meu caminho."
    },
    {
      "number": 106,
      "text": "Jurei, e o cumprirei, que guardarei os teus justos juízos."
    },
    {
      "number": 107,
      "text": "Estou aflitíssimo; vivifica-me, ó Senhor, segundo a tua palavra."
    },
    {
      "number": 108,
      "text": "Aceita, eu te rogo, as oferendas voluntárias da minha boca, ó Senhor; ensina-me os teus juízos."
    },
    {
      "number": 109,
      "text": "A minha alma está de contínuo nas minhas mãos; todavia não me esqueço da tua lei."
    },
    {
      "number": 110,
      "text": "Os ímpios me armaram laço; contudo não me desviei dos teus preceitos."
    },
    {
      "number": 111,
      "text": "Os teus testemunhos tenho eu tomado por herança para sempre, pois são o gozo do meu coração."
    },
    {
      "number": 112,
      "text": "Inclinei o meu coração a guardar os teus estatutos, para sempre, até ao fim."
    },
    { "number": 113, "text": "Odeio os pensamentos vãos, mas amo a tua lei." },
    {
      "number": 114,
      "text": "Tu és o meu refúgio e o meu escudo; espero na tua palavra."
    },
    {
      "number": 115,
      "text": "Apartai-vos de mim, malfeitores, pois guardarei os mandamentos do meu Deus."
    },
    {
      "number": 116,
      "text": "Sustenta-me conforme a tua palavra, para que viva, e não me deixes envergonhado da minha esperança."
    },
    {
      "number": 117,
      "text": "Sustenta-me, e serei salvo, e de contínuo terei respeito aos teus estatutos."
    },
    {
      "number": 118,
      "text": "Tu tens pisado aos pés todos os que se desviam dos teus estatutos, pois o engano deles é falsidade."
    },
    {
      "number": 119,
      "text": "Tu tiraste da terra todos os ímpios, como a escória, por isso amo os teus testemunhos."
    },
    {
      "number": 120,
      "text": "O meu corpo se arrepiou com temor de ti, e temi os teus juízos."
    },
    {
      "number": 121,
      "text": "Fiz juízo e justiça; não me entregues aos meus opressores."
    },
    {
      "number": 122,
      "text": "Fica por fiador do teu servo para o bem; não deixes que os soberbos me oprimam."
    },
    {
      "number": 123,
      "text": "Os meus olhos desfaleceram pela tua salvação e pela promessa da tua justiça."
    },
    {
      "number": 124,
      "text": "Usa com o teu servo segundo a tua benignidade, e ensina-me os teus estatutos."
    },
    {
      "number": 125,
      "text": "Sou teu servo; dá-me inteligência, para entender os teus testemunhos."
    },
    {
      "number": 126,
      "text": "Já é tempo de operares, ó Senhor, pois eles têm quebrantado a tua lei."
    },
    { "number": 127, "text": "Por isso am" },
    {
      "number": 128,
      "text": "Por isso estimo todos os teus preceitos acerca de tudo, como retos, e odeio toda falsa vereda."
    },
    {
      "number": 129,
      "text": "Maravilhosos são os teus testemunhos; portanto, a minha alma os guarda."
    },
    {
      "number": 130,
      "text": "A entrada das tuas palavras dá luz, dá entendimento aos símplices."
    },
    {
      "number": 131,
      "text": "Abri a minha boca, e respirei, pois que desejei os teus mandamentos."
    },
    {
      "number": 132,
      "text": "Olha para mim, e tem piedade de mim, conforme usas com os que amam o teu nome."
    },
    {
      "number": 133,
      "text": "Ordena os meus passos na tua palavra, e não se apodere de mim iniqüidade alguma."
    },
    {
      "number": 134,
      "text": "Livra-me da opressão do homem; assim guardarei os teus preceitos."
    },
    {
      "number": 135,
      "text": "Faze resplandecer o teu rosto sobre o teu servo, e ensina-me os teus estatutos."
    },
    {
      "number": 136,
      "text": "Rios de águas correm dos meus olhos, porque não guardam a tua lei."
    },
    {
      "number": 137,
      "text": "Justo és, ó Senhor, e retos são os teus juízos."
    },
    {
      "number": 138,
      "text": "Os teus testemunhos que ordenaste são retos e muito fiéis."
    },
    {
      "number": 139,
      "text": "O meu zelo me consumiu, porque os meus inimigos se esqueceram da tua palavra."
    },
    {
      "number": 140,
      "text": "A tua palavra é muito pura; portanto, o teu servo a ama."
    },
    {
      "number": 141,
      "text": "Pequeno sou e desprezado, porém não me esqueço dos teus mandamentos."
    },
    {
      "number": 142,
      "text": "A tua justiça é uma justiça eterna, e a tua lei é a verdade."
    },
    {
      "number": 143,
      "text": "Aflição e angústia se apoderam de mim; contudo os teus mandamentos são o meu prazer."
    },
    {
      "number": 144,
      "text": "A justiça dos teus testemunhos é eterna; dá-me inteligência, e viverei."
    },
    {
      "number": 145,
      "text": "Clamei de todo o meu coração; escuta-me, Senhor, e guardarei os teus estatutos."
    },
    {
      "number": 146,
      "text": "A ti te invoquei; salva-me, e guardarei os teus testemunhos."
    },
    {
      "number": 147,
      "text": "Antecipei o cair da noite, e clamei; esperei na tua palavra."
    },
    {
      "number": 148,
      "text": "Os meus olhos anteciparam as vigílias da noite, para meditar na tua palavra."
    },
    {
      "number": 149,
      "text": "Ouve a minha voz, segundo a tua benignidade; vivifica-me, ó Senhor, segundo o teu juízo."
    },
    {
      "number": 150,
      "text": "Aproximam-se os que se dão a maus tratos; afastam-se da tua lei."
    },
    {
      "number": 151,
      "text": "Tu estás perto, ó Senhor, e todos os teus mandamentos são a verdade."
    },
    {
      "number": 152,
      "text": "Acerca dos teus testemunhos soube, desde a antiguidade, que tu os fundaste para sempre."
    },
    {
      "number": 153,
      "text": "Olha para a minha aflição, e livra-me, pois não me esqueci da tua lei."
    },
    {
      "number": 154,
      "text": "Pleiteia a minha causa, e livra-me; vivifica-me segundo a tua palavra."
    },
    {
      "number": 155,
      "text": "A salvação está longe dos ímpios, pois não buscam os teus estatutos."
    },
    {
      "number": 156,
      "text": "Muitas são, ó Senhor, as tuas misericórdias; vivifica-me segundo os teus juízos."
    },
    {
      "number": 157,
      "text": "Muitos são os meus perseguidores e os meus inimigos; mas não me desvio dos teus testemunhos."
    },
    {
      "number": 158,
      "text": "Vi os transgressores, e me afligi, porque não observam a tua palavra."
    },
    {
      "number": 159,
      "text": "Considera como amo os teus preceitos; vivifica-me, ó Senhor, segundo a tua benignidade."
    },
    {
      "number": 160,
      "text": "A tua palavra é a verdade desde o princípio, e cada um dos teus juízos dura para sempre."
    },
    {
      "number": 161,
      "text": "Príncipes me perseguiram sem causa, mas o meu coração temeu a tua palavra."
    },
    {
      "number": 162,
      "text": "Folgo com a tua palavra, como aquele que acha um grande despojo."
    },
    { "number": 163, "text": "Abomino e odeio a mentira; mas amo a tua lei." },
    {
      "number": 164,
      "text": "Sete vezes no dia te louvo pelos juízos da tua justiça."
    },
    {
      "number": 165,
      "text": "Muita paz têm os que amam a tua lei, e para eles não há tropeço."
    },
    {
      "number": 166,
      "text": "Senhor, tenho esperado na tua salvação, e tenho cumprido os teus mandamentos."
    },
    {
      "number": 167,
      "text": "A minha alma tem observado os teus testemunhos; amo-os excessivamente."
    },
    {
      "number": 168,
      "text": "Tenho observado os teus preceitos, e os teus testemunhos, porque todos os meus caminhos estão diante de ti."
    },
    {
      "number": 169,
      "text": "Chegue a ti o meu clamor, ó Senhor; dá-me entendimento conforme a tua palavra."
    },
    {
      "number": 170,
      "text": "Chegue a minha súplica perante a tua face; livra-me segundo a tua palavra."
    },
    {
      "number": 171,
      "text": "Os meus lábios proferiram o louvor, quando me ensinaste os teus estatutos."
    },
    {
      "number": 172,
      "text": "A minha língua falará da tua palavra, pois todos os teus mandamentos são justiça."
    },
    {
      "number": 173,
      "text": "Venha a tua mão socorrer-me, pois escolhi os teus preceitos."
    },
    {
      "number": 174,
      "text": "Tenho desejado a tua salvação, ó Senhor; a tua lei é todo o meu prazer."
    },
    {
      "number": 175,
      "text": "Viva a minha alma, e louvar-te-á; ajudem-me os teus juízos."
    },
    {
      "number": 176,
      "text": "Desgarrei-me como a ovelha perdida; busca o teu servo, pois não me esqueci dos teus mandamentos."
    }
  ]
}
