{
  "book": {
    "abbrev": { "pt": "sl", "en": "ps" },
    "name": "Salmos",
    "author": "David, Moisés, Salomão",
    "group": "Poéticos",
    "version": "rvr"
  },
  "chapter": { "number": 57, "verses": 11 },
  "verses": [
    {
      "number": 1,
      "text": "TEN misericordia de mí, oh Dios, ten misericordia de mí; Porque en ti ha confiado mi alma, Y en la sombra de tus alas me ampararé, Hasta que pasen los quebrantos."
    },
    {
      "number": 2,
      "text": "Clamaré al Dios Altísimo, Al Dios que me favorece."
    },
    {
      "number": 3,
      "text": "El enviará desde los cielos, y me salvará De la infamia del que me apura; (Selah) Dios enviará su misericordia y su verdad."
    },
    {
      "number": 4,
      "text": "Mi vida está entre leones; Estoy echado entre hijos de hombres encendidos: Sus dientes son lanzas y saetas, Y su lengua cuchillo agudo."
    },
    {
      "number": 5,
      "text": "Ensálzate sobre los cielos, oh Dios; Sobre toda la tierra tu gloria."
    },
    {
      "number": 6,
      "text": "Red han armado á mis pasos; Hase abatido mi alma: Hoyo han cavado delante de mí; En medio de él han caído. (Selah.)"
    },
    {
      "number": 7,
      "text": "Pronto está mi corazón, oh Dios, mi corazón está dispuesto: Cantaré, y trovaré salmos."
    },
    {
      "number": 8,
      "text": "Despierta, oh gloria mía; despierta, salterio y arpa: Levantaréme de mañana."
    },
    {
      "number": 9,
      "text": "Alabarte he en los pueblos, oh Señor; Cantaré de ti en las naciones."
    },
    {
      "number": 10,
      "text": "Porque grande es hasta los cielos tu misericordia, Y hasta las nubes tu verdad."
    },
    {
      "number": 11,
      "text": "Ensálzate sobre los cielos, oh Dios; Sobre toda la tierra tu gloria."
    }
  ]
}
